MANIFEST.in
README.md
setup.py
pysubway/__init__.py
pysubway/cache.py
pysubway/domain.py
pysubway/errors.py
pysubway/log.py
pysubway/request.py
pysubway/response.py
pysubway/router.py
pysubway/view.py
pysubway.egg-info/PKG-INFO
pysubway.egg-info/SOURCES.txt
pysubway.egg-info/dependency_links.txt
pysubway.egg-info/requires.txt
pysubway.egg-info/top_level.txt
pysubway/apps/__init__.py
pysubway/apps/demo_01/__init__.py
pysubway/apps/demo_01/main.py
pysubway/apps/inner_platform/__init__.py
pysubway/async_task/__init__.py
pysubway/async_task/celery.py
pysubway/async_task/conf.py
pysubway/async_task/task_base.py
pysubway/async_task/task_inner_platform.py
pysubway/async_task/task_notification.py
pysubway/async_task/task_xinyan.py
pysubway/conf/__init__.py
pysubway/conf/log.py
pysubway/conf/app_template/__init__.py
pysubway/conf/app_template/conf/__init__.py
pysubway/gitignore/batch_test/__init__.py
pysubway/gitignore/batch_test/gunicorn.py
pysubway/gitignore/batch_test/main.py
pysubway/gitignore/batch_test/mainv2.py
pysubway/gitignore/batch_test/mainv3.py
pysubway/gitignore/batch_test/mainv3_1.py
pysubway/gitignore/batch_test/mainv4.py
pysubway/gitignore/batch_test/batch_huadao/__init__.py
pysubway/gitignore/batch_test/batch_huadao/batch.py
pysubway/gitignore/batch_test/static/__init__.py
pysubway/model/__init__.py
pysubway/model/block.py
pysubway/model/role.py
pysubway/model/role_permission.py
pysubway/model/user.py
pysubway/model/guard/__init__.py
pysubway/model/guard/company.py
pysubway/model/guard/company_product.py
pysubway/model/guard/company_recharge_journal.py
pysubway/model/guard/product.py
pysubway/service/__init__.py
pysubway/service/aliyun/__init__.py
pysubway/service/aliyun/oss.py
pysubway/service/aliyun/uemail.py
pysubway/service/aliyun/dingding/__init__.py
pysubway/service/aliyun/dingding/robot.py
pysubway/service/aliyun/docker/__init__.py
pysubway/service/aliyun/log_service/__init__.py
pysubway/service/aliyun/log_service/clean_log.py
pysubway/service/authentication/__init__.py
pysubway/service/authentication/auth_mongo.py
pysubway/service/authentication/auth_mysql.py
pysubway/service/authentication/base.py
