Metadata-Version: 1.0
Name: pysubway
Version: 0.1.7
Summary: build on flask
Home-page: https://github.com/kougazhang
Author: kougazhang
Author-email: kougazhang@gmail.com
License: UNKNOWN
Platform: UNKNOWN
